{
    "similarPosts": [
        {
            "image": {
                "src": "posts/1",
                "ext": "png"
            },
            "title": "События жизненного цикла ReactJS",
            "date": "12 декабря",
            "datetime": "2024-12-12"
        },
        {
            "image": {
                "src": "posts/2",
                "ext": "png"
            },
            "title": "CSS Grids. Полное руководство",
            "date": "10 декабря",
            "datetime": "2024-12-10"
        },
        {
            "image": {
                "src": "posts/3",
                "ext": "png"
            },
            "title": "Асинхронность в JavaScript",
            "date": "5 декабря",
            "datetime": "2024-12-5"
        }
    ]
}